napari_mat_images.py
napari_mat_images-0.1.3.dist-info/AUTHORS.md
napari_mat_images-0.1.3.dist-info/LICENSE
napari_mat_images-0.1.3.dist-info/METADATA
napari_mat_images-0.1.3.dist-info/WHEEL
napari_mat_images-0.1.3.dist-info/entry_points.txt
napari_mat_images-0.1.3.dist-info/top_level.txt
napari_mat_images-0.1.3.dist-info/RECORD
