Metadata-Version: 2.1
Name: napari-mat-images
Version: 0.1.3
Summary: A plugin to load images stored in MATLAB .mat files with napari
Home-page: https://github.com/hectormz/napari-mat-images
Author: Hector Munoz
Author-email: hectormz.git@gmail.com
Maintainer: Hector Munoz
Maintainer-email: hectormz.git@gmail.com
License: BSD-3
Platform: UNKNOWN
Classifier: Development Status :: 4 - Beta
Classifier: Intended Audience :: Developers
Classifier: Framework :: napari
Classifier: Topic :: Software Development :: Testing
Classifier: Programming Language :: Python
Classifier: Programming Language :: Python :: 3
Classifier: Programming Language :: Python :: 3.6
Classifier: Programming Language :: Python :: 3.7
Classifier: Programming Language :: Python :: 3.8
Classifier: Programming Language :: Python :: 3.9
Classifier: Programming Language :: Python :: Implementation :: CPython
Classifier: Programming Language :: Python :: Implementation :: PyPy
Classifier: Operating System :: OS Independent
Classifier: License :: OSI Approved :: BSD License
Requires-Python: >=3.6
Requires-Dist: dask[delayed]
Requires-Dist: h5py
Requires-Dist: numpy
Requires-Dist: pluggy
Requires-Dist: scipy
